{
  "id": "",
  "name": "",
  "font_family": "iconfont",
  "css_prefix_text": "icon-",
  "description": "",
  "glyphs": [
    {
      "icon_id": "694111",
      "name": "尾页",
      "font_class": "weiye",
      "unicode": "e68c",
      "unicode_decimal": 59020
    },
    {
      "icon_id": "2488128",
      "name": "上一页",
      "font_class": "shangyiye",
      "unicode": "e615",
      "unicode_decimal": 58901
    },
    {
      "icon_id": "2488136",
      "name": "下一页",
      "font_class": "xiayiye",
      "unicode": "e61a",
      "unicode_decimal": 58906
    },
    {
      "icon_id": "6129085",
      "name": "49最后一页、末页、下一首",
      "font_class": "zuihouyiyemoyexiayishou",
      "unicode": "e76d",
      "unicode_decimal": 59245
    },
    {
      "icon_id": "6129086",
      "name": "48第一页、首页、上一首",
      "font_class": "diyiyeshouyeshangyishou",
      "unicode": "e76e",
      "unicode_decimal": 59246
    }
  ]
}
